ValidateField/__init__.py
Validandolosdatosdelprofile-0.0.2.dist-info/METADATA
Validandolosdatosdelprofile-0.0.2.dist-info/WHEEL
Validandolosdatosdelprofile-0.0.2.dist-info/top_level.txt
Validandolosdatosdelprofile-0.0.2.dist-info/RECORD
