Metadata-Version: 2.1
Name: Validandolosdatosdelprofile
Version: 0.0.2
Summary: Aquí debes incluir una descripción corta de la librería
Home-page: UNKNOWN
Author: XXXX XXXXX
Author-email: XXX@gmail.com
License: MIT
Platform: UNKNOWN
